mcp_common/__init__.py
mcp_common/config.py
mcp_common/gpu_manager.py
mcp_common/serialization.py
mcp_common/task_manager.py
scicomp_mcp_common-0.1.6.dist-info/METADATA
scicomp_mcp_common-0.1.6.dist-info/WHEEL
scicomp_mcp_common-0.1.6.dist-info/RECORD
